setup.py
lib/rhevm/__init__.py
lib/rhevm/_version.py
lib/rhevm/api.py
lib/rhevm/appcfg.py
lib/rhevm/application.py
lib/rhevm/collection.py
lib/rhevm/error.py
lib/rhevm/pool.py
lib/rhevm/powershell.py
lib/rhevm/util.py
lib/rhevm/module/__init__.py
lib/rhevm/module/datacenter.py
lib/rhevm/module/disk.py
lib/rhevm/module/iso.py
lib/rhevm/module/nic.py
lib/rhevm/module/tag.py
lib/rhevm/module/task.py
lib/rhevm/module/ticket.py
lib/rhevm/module/vm.py
lib/rhevm/module/vmcontrol.py
lib/rhevm/test/__init__.py
lib/rhevm/test/base.py
lib/rhevm/test/test_datacenter.py
lib/rhevm/test/test_disk.py
lib/rhevm/test/test_nic.py
lib/rhevm/test/test_powershell.py
lib/rhevm/test/test_tag.py
lib/rhevm/test/test_ticket.py
lib/rhevm/test/test_vm.py
lib/rhevm/test/test_vmcontrol.py
lib/rhevm_api.egg-info/PKG-INFO
lib/rhevm_api.egg-info/SOURCES.txt
lib/rhevm_api.egg-info/dependency_links.txt
lib/rhevm_api.egg-info/entry_points.txt
lib/rhevm_api.egg-info/requires.txt
lib/rhevm_api.egg-info/top_level.txt