Metadata-Version: 1.0
Name: rhevm-api
Version: 0.9.0
Summary: A REST mapping of the PowerShell API of RHEV-M.
Home-page: http://bitbucket.org/geertj/rhevm-api
Author: Geert Jansen
Author-email: geert@boskant.nl
License: MIT
Platform: UNKNOWN
Classifier: Development Status :: 3 - Alpha
Classifier: Environment :: Console
Classifier: Environment :: Web Environment
Classifier: Intended Audience :: Developers
Classifier: Intended Audience :: Information Technology
Classifier: License :: OSI Approved :: MIT License
Classifier: Operating System :: Microsoft :: Windows
Classifier: Programming Language :: Python
Classifier: Topic :: Internet :: WWW/HTTP :: WSGI :: Application
